{
  "main": {
    "id": "5202cb91addcd1ea",
    "type": "split",
    "children": [
      {
        "id": "5d051a71839b35a0",
        "type": "tabs",
        "children": [
          {
            "id": "26447a51908c7296",
            "type": "leaf",
            "state": {
              "type": "markdown",
              "state": {
                "file": "Tester-QA/QA.md",
                "mode": "source",
                "source": false
              },
              "icon": "lucide-file",
              "title": "QA"
            }
          }
        ]
      }
    ],
    "direction": "vertical"
  },
  "left": {
    "id": "14135a00615a046f",
    "type": "split",
    "children": [
      {
        "id": "d0deb8b4fc489bf6",
        "type": "tabs",
        "children": [
          {
            "id": "f33de1092e0637a2",
            "type": "leaf",
            "state": {
              "type": "file-explorer",
              "state": {
                "sortOrder": "alphabetical"
              },
              "icon": "lucide-folder-closed",
              "title": "Explorador de archivos"
            }
          },
          {
            "id": "4b6ced4f4525f95c",
            "type": "leaf",
            "state": {
              "type": "search",
              "state": {
                "query": "tag:#928b78",
                "matchingCase": false,
                "explainSearch": false,
                "collapseAll": false,
                "extraContext": false,
                "sortOrder": "alphabetical"
              },
              "icon": "lucide-search",
              "title": "Buscar"
            }
          },
          {
            "id": "314b0cdf03c91856",
            "type": "leaf",
            "state": {
              "type": "bookmarks",
              "state": {},
              "icon": "lucide-bookmark",
              "title": "Marcadores"
            }
          }
        ]
      }
    ],
    "direction": "horizontal",
    "width": 249
  },
  "right": {
    "id": "beb245da41462fbc",
    "type": "split",
    "children": [
      {
        "id": "b5340651c20e9937",
        "type": "tabs",
        "children": [
          {
            "id": "3650054b2a9f7331",
            "type": "leaf",
            "state": {
              "type": "backlink",
              "state": {
                "file": "prueba 101.md",
                "collapseAll": false,
                "extraContext": false,
                "sortOrder": "alphabetical",
                "showSearch": false,
                "searchQuery": "",
                "backlinkCollapsed": false,
                "unlinkedCollapsed": true
              },
              "icon": "links-coming-in",
              "title": "Enlaces entrantes de prueba 101"
            }
          },
          {
            "id": "57411fe99c7d0b16",
            "type": "leaf",
            "state": {
              "type": "outgoing-link",
              "state": {
                "file": "prueba 101.md",
                "linksCollapsed": false,
                "unlinkedCollapsed": true
              },
              "icon": "links-going-out",
              "title": "Enlaces salientes de prueba 101"
            }
          },
          {
            "id": "08280d71ab2b4238",
            "type": "leaf",
            "state": {
              "type": "tag",
              "state": {
                "sortOrder": "frequency",
                "useHierarchy": true
              },
              "icon": "lucide-tags",
              "title": "Etiquetas"
            }
          },
          {
            "id": "04901dd05d63015d",
            "type": "leaf",
            "state": {
              "type": "outline",
              "state": {
                "file": "prueba 101.md"
              },
              "icon": "lucide-list",
              "title": "Esquema de prueba 101"
            }
          }
        ]
      }
    ],
    "direction": "horizontal",
    "width": 300,
    "collapsed": true
  },
  "left-ribbon": {
    "hiddenItems": {
      "switcher:Abrir selector rápido": false,
      "graph:Abrir vista gráfica": false,
      "canvas:Crear nuevo lienzo": false,
      "daily-notes:Abrir la nota de hoy": false,
      "templates:Insertar plantilla": false,
      "command-palette:Abrir paleta de comandos": false,
      "obsidian-excalidraw-plugin:Create new drawing": false
    }
  },
  "active": "26447a51908c7296",
  "lastOpenFiles": [
    "Clamoxin.md",
    "Gasto mes.md",
    "Gatos negocio.md",
    "Ideas instagram.md",
    "Journaling relacion.md",
    "Tareas Xubax.md",
    "Pasted image 20240806153629.png",
    "prueba 101.md",
    "Negocios/ideas de negocio.md",
    "Borradores/Markdown Basico.md",
    "Personal/Terapia/Sonia Psi/Junio 16-23.md",
    "Borradores/Fuentes.md",
    "Libros/Como ganar amigos/Como ganar amigos e influir sobre las personas.md",
    "Negocios/Podcats.md",
    "Negocios/Fotografía Eventos.md",
    "Negocios/Crear Youtubers,Intagamers.md",
    "Negocios/Crear un Side Project.md",
    "Personal/Pensamientos extendidos/Avanzar/Avanzar.md",
    "Personas/Moni Helia Hernandez Moli.md",
    "Personas/Fer GC.md",
    "Personas/Diana C.md",
    "Python/Basico.md",
    "¡Hola !¡Gracias por tu interés! 😊 Nos encantaría que vinieras a Dona Delicia en Doctor Coss. Tenemos unas donas deliciosas que seguro te van a encantar, además de un café que combina perfecto con ellas..md",
    "Comandos xubax.md",
    "lista usuarios owncloud.md",
    "Gogo's.md",
    "xubax.md",
    "Sin título 3.canvas",
    "Sin título 2.canvas",
    "Sin título 1.canvas",
    "Sin título.canvas",
    "Excalidraw",
    "Data/Basico Data",
    "Kotlin",
    "Data",
    "Python",
    "Tester-QA"
  ]
}